zingmp3py/__init__.py
zingmp3py/sobj.py
zingmp3py/util.py
zingmp3py/zasync.py
zingmp3py/zsync.py
zingmp3py-0.3.3.dist-info/LICENSE
zingmp3py-0.3.3.dist-info/METADATA
zingmp3py-0.3.3.dist-info/WHEEL
zingmp3py-0.3.3.dist-info/top_level.txt
zingmp3py-0.3.3.dist-info/RECORD
