Metadata-Version: 2.1
Name: zingmp3py
Version: 0.3.3
Summary: A light weight Python library for the ZingMp3 API
Author: The DT
Author-email: duongtuan30306@gmail.com
License-File: LICENSE
Requires-Dist: aiohttp
Requires-Dist: requests
